{
  "attributes": [
    {
      "allow_nil?": false,
      "default": "fragment(\"gen_random_uuid()\")",
      "generated?": false,
      "precision": null,
      "primary_key?": true,
      "references": null,
      "scale": null,
      "size": null,
      "source": "template_id",
      "type": "uuid"
    },
    {
      "allow_nil?": false,
      "default": "nil",
      "generated?": false,
      "precision": null,
      "primary_key?": false,
      "references": null,
      "scale": null,
      "size": null,
      "source": "name",
      "type": "text"
    },
    {
      "allow_nil?": false,
      "default": "nil",
      "generated?": false,
      "precision": null,
      "primary_key?": false,
      "references": null,
      "scale": null,
      "size": null,
      "source": "description",
      "type": "text"
    },
    {
      "allow_nil?": false,
      "default": "nil",
      "generated?": false,
      "precision": null,
      "primary_key?": false,
      "references": null,
      "scale": null,
      "size": null,
      "source": "category",
      "type": "text"
    },
    {
      "allow_nil?": false,
      "default": "nil",
      "generated?": false,
      "precision": null,
      "primary_key?": false,
      "references": null,
      "scale": null,
      "size": null,
      "source": "preferences",
      "type": "map"
    },
    {
      "allow_nil?": false,
      "default": "\"private\"",
      "generated?": false,
      "precision": null,
      "primary_key?": false,
      "references": null,
      "scale": null,
      "size": null,
      "source": "template_type",
      "type": "text"
    },
    {
      "allow_nil?": false,
      "default": "nil",
      "generated?": false,
      "precision": null,
      "primary_key?": false,
      "references": {
        "deferrable": false,
        "destination_attribute": "id",
        "destination_attribute_default": null,
        "destination_attribute_generated": null,
        "index?": false,
        "match_type": null,
        "match_with": null,
        "multitenancy": {
          "attribute": null,
          "global": null,
          "strategy": null
        },
        "name": "preference_templates_created_by_fkey",
        "on_delete": "nilify",
        "on_update": null,
        "primary_key?": true,
        "schema": "public",
        "table": "users"
      },
      "scale": null,
      "size": null,
      "source": "created_by",
      "type": "uuid"
    },
    {
      "allow_nil?": false,
      "default": "1",
      "generated?": false,
      "precision": null,
      "primary_key?": false,
      "references": null,
      "scale": null,
      "size": null,
      "source": "version",
      "type": "bigint"
    },
    {
      "allow_nil?": false,
      "default": "0",
      "generated?": false,
      "precision": null,
      "primary_key?": false,
      "references": null,
      "scale": null,
      "size": null,
      "source": "usage_count",
      "type": "bigint"
    },
    {
      "allow_nil?": true,
      "default": "nil",
      "generated?": false,
      "precision": null,
      "primary_key?": false,
      "references": null,
      "scale": null,
      "size": null,
      "source": "rating",
      "type": "decimal"
    },
    {
      "allow_nil?": false,
      "default": "0",
      "generated?": false,
      "precision": null,
      "primary_key?": false,
      "references": null,
      "scale": null,
      "size": null,
      "source": "rating_count",
      "type": "bigint"
    },
    {
      "allow_nil?": false,
      "default": "[]",
      "generated?": false,
      "precision": null,
      "primary_key?": false,
      "references": null,
      "scale": null,
      "size": null,
      "source": "tags",
      "type": [
        "array",
        "text"
      ]
    },
    {
      "allow_nil?": false,
      "default": "nil",
      "generated?": false,
      "precision": null,
      "primary_key?": false,
      "references": null,
      "scale": null,
      "size": null,
      "source": "compatible_versions",
      "type": [
        "array",
        "text"
      ]
    },
    {
      "allow_nil?": false,
      "default": "false",
      "generated?": false,
      "precision": null,
      "primary_key?": false,
      "references": null,
      "scale": null,
      "size": null,
      "source": "featured",
      "type": "boolean"
    },
    {
      "allow_nil?": false,
      "default": "false",
      "generated?": false,
      "precision": null,
      "primary_key?": false,
      "references": null,
      "scale": null,
      "size": null,
      "source": "deprecated",
      "type": "boolean"
    },
    {
      "allow_nil?": true,
      "default": "nil",
      "generated?": false,
      "precision": null,
      "primary_key?": false,
      "references": {
        "deferrable": false,
        "destination_attribute": "template_id",
        "destination_attribute_default": null,
        "destination_attribute_generated": null,
        "index?": false,
        "match_type": null,
        "match_with": null,
        "multitenancy": {
          "attribute": null,
          "global": null,
          "strategy": null
        },
        "name": "preference_templates_replacement_template_id_fkey",
        "on_delete": null,
        "on_update": null,
        "primary_key?": true,
        "schema": "public",
        "table": "preference_templates"
      },
      "scale": null,
      "size": null,
      "source": "replacement_template_id",
      "type": "uuid"
    },
    {
      "allow_nil?": false,
      "default": "fragment(\"(now() AT TIME ZONE 'utc')\")",
      "generated?": false,
      "precision": null,
      "primary_key?": false,
      "references": null,
      "scale": null,
      "size": null,
      "source": "inserted_at",
      "type": "utc_datetime_usec"
    },
    {
      "allow_nil?": false,
      "default": "fragment(\"(now() AT TIME ZONE 'utc')\")",
      "generated?": false,
      "precision": null,
      "primary_key?": false,
      "references": null,
      "scale": null,
      "size": null,
      "source": "updated_at",
      "type": "utc_datetime_usec"
    }
  ],
  "base_filter": null,
  "check_constraints": [],
  "custom_indexes": [],
  "custom_statements": [],
  "has_create_action": true,
  "hash": "969AEC9D417A7F16465D1B9A95F79D88F2A95758541D98D5F1138403A3108B27",
  "identities": [
    {
      "all_tenants?": false,
      "base_filter": null,
      "index_name": "preference_templates_unique_template_name_index",
      "keys": [
        {
          "type": "atom",
          "value": "name"
        },
        {
          "type": "atom",
          "value": "created_by"
        }
      ],
      "name": "unique_template_name",
      "nils_distinct?": true,
      "where": null
    }
  ],
  "multitenancy": {
    "attribute": null,
    "global": null,
    "strategy": null
  },
  "repo": "Elixir.RubberDuck.Repo",
  "schema": null,
  "table": "preference_templates"
}